mcci_api/__init__.py
mcci_api/_exceptions.py
mcci_api/types.py
mcci_api-24.5.6.dev1.dist-info/LICENSES/CC-BY-4.0.txt
mcci_api-24.5.6.dev1.dist-info/LICENSES/CC0-1.0.txt
mcci_api-24.5.6.dev1.dist-info/LICENSES/MIT.txt
mcci_api-24.5.6.dev1.dist-info/METADATA
mcci_api-24.5.6.dev1.dist-info/WHEEL
mcci_api-24.5.6.dev1.dist-info/RECORD
