Metadata-Version: 2.1
Name: mcci-api
Version: 24.5.6.dev1
Summary: Unofficial Python bindings to the MCC Island API.
Home-page: https://github.com/osfanbuff63/mcci-api-python
License: MIT
Author: osfanbuff63
Author-email: 91388253+osfanbuff63@users.noreply.github.com
Requires-Python: >=3.12,<4.0
Classifier: License :: OSI Approved :: MIT License
Classifier: Programming Language :: Python :: 3
Classifier: Programming Language :: Python :: 3.12
Requires-Dist: gql[httpx] (>=3.5.0,<4.0.0)
Requires-Dist: mypy (>=1.10.0,<2.0.0)
Project-URL: Repository, https://github.com/osfanbuff63/mcci-api-python
